nebpack.py
setup.py
nebpack.egg-info/PKG-INFO
nebpack.egg-info/SOURCES.txt
nebpack.egg-info/dependency_links.txt
nebpack.egg-info/not-zip-safe
nebpack.egg-info/requires.txt
nebpack.egg-info/top_level.txt