Metadata-Version: 1.0
Name: nebpack
Version: 0.0.3
Summary: Store annotations in Git repositories.
Home-page: http://github.com/davisp/nebpack
Author: Paul Joseph Davis
Author-email: davisp@neb.com
License: MIT
Keywords: bioinformatics git annotations
Platform: any
Classifier: Development Status :: 3 - Alpha
Classifier: Intended Audience :: Developers
Classifier: Intended Audience :: Science/Research
Classifier: License :: OSI Approved :: MIT License
Classifier: Natural Language :: English
Classifier: Operating System :: OS Independent
Classifier: Programming Language :: Python
Classifier: Topic :: Scientific/Engineering :: Bio-Informatics
Classifier: Topic :: Software Development :: Libraries :: Python Modules
